sporestack/__init__.py
sporestack/_cli_utils.py
sporestack/api.py
sporestack/api_client.py
sporestack/cli.py
sporestack/client.py
sporestack/constants.py
sporestack/exceptions.py
sporestack/models.py
sporestack/py.typed
sporestack/utils.py
sporestack-14.4.0.dist-info/entry_points.txt
sporestack-14.4.0.dist-info/LICENSE.txt
sporestack-14.4.0.dist-info/WHEEL
sporestack-14.4.0.dist-info/METADATA
sporestack-14.4.0.dist-info/RECORD
