Metadata-Version: 2.3
Name: sporestack
Version: 14.4.0
Summary: SporeStack API library and CLI for launching servers with Monero or Bitcoin
Keywords: bitcoin,monero,vps,server
Author-email: SporeStack <support@sporestack.com>
Requires-Python: ~=3.9
Requires-Dist: pydantic>=1.10,<3
Requires-Dist: httpx[socks]>=0.28.0
Requires-Dist: segno ; extra == "cli"
Requires-Dist: typer>=0.9.0 ; extra == "cli"
Requires-Dist: rich ; extra == "cli"
Project-URL: Changelog, https://git.sporestack.com/SporeStack/sporestack-python/src/branch/master/CHANGELOG.md
Project-URL: Homepage, https://sporestack.com
Project-URL: Source, https://git.sporestack.com/SporeStack/sporestack-python
Provides-Extra: cli
